diamond4py-0.0.6.data/data/CMakeLists.txt
diamond4py-0.0.6.data/data/FindLAPACKEXT.cmake
diamond4py-0.0.6.data/data/FindLAPACKE.cmake
diamond4py-0.0.6.data/data/src/run/double_indexed.cpp
diamond4py-0.0.6.data/data/src/run/tools.cpp
diamond4py-0.0.6.data/data/src/run/main.cpp
diamond4py-0.0.6.data/data/src/run/main.h
diamond4py-0.0.6.data/data/src/run/config.h
diamond4py-0.0.6.data/data/src/run/workflow.h
diamond4py-0.0.6.data/data/src/run/tools.h
diamond4py-0.0.6.data/data/src/run/config.cpp
diamond4py-0.0.6.data/data/src/search/kmer_ranking.cpp
diamond4py-0.0.6.data/data/src/search/search.h
diamond4py-0.0.6.data/data/src/search/seed_complexity.cpp
diamond4py-0.0.6.data/data/src/search/setup.cpp
diamond4py-0.0.6.data/data/src/search/sse_dist.h
diamond4py-0.0.6.data/data/src/search/left_most.h
diamond4py-0.0.6.data/data/src/search/kmer_ranking.h
diamond4py-0.0.6.data/data/src/search/stage2.cpp
diamond4py-0.0.6.data/data/src/search/hit.h
diamond4py-0.0.6.data/data/src/search/stage0.cpp
diamond4py-0.0.6.data/data/src/search/finger_print.h
diamond4py-0.0.6.data/data/src/search/seed_complexity.h
diamond4py-0.0.6.data/data/src/test/test_cases.cpp
diamond4py-0.0.6.data/data/src/test/test.cpp
diamond4py-0.0.6.data/data/src/test/test.h
diamond4py-0.0.6.data/data/src/test/data.cpp
diamond4py-0.0.6.data/data/src/legacy/util/task_queue.h
diamond4py-0.0.6.data/data/src/cluster/cluster_registry.h
diamond4py-0.0.6.data/data/src/cluster/cluster.h
diamond4py-0.0.6.data/data/src/cluster/reassign.cpp
diamond4py-0.0.6.data/data/src/cluster/realign.cpp
diamond4py-0.0.6.data/data/src/cluster/helpers.cpp
diamond4py-0.0.6.data/data/src/cluster/cluster_registry.cpp
diamond4py-0.0.6.data/data/src/cluster/output.cpp
diamond4py-0.0.6.data/data/src/cluster/cascaded/recluster.cpp
diamond4py-0.0.6.data/data/src/cluster/cascaded/helpers.cpp
diamond4py-0.0.6.data/data/src/cluster/cascaded/wrapper.cpp
diamond4py-0.0.6.dist-info/WHEEL
diamond4py-0.0.6.dist-info/LICENSE
diamond4py-0.0.6.dist-info/RECORD
diamond4py-0.0.6.dist-info/top_level.txt
diamond4py-0.0.6.dist-info/METADATA
