Metadata-Version: 2.1
Name: diamond4py
Version: 0.0.6
Summary: Diamond Python bindings for sequence alignment
Author-email: "Zhang.H.N" <zhang.h.n@foxmail.com>
License: GPLv3
Project-URL: Homepage, https://github.com/GCS-ZHN/diamond4py
Project-URL: Bug Tracker, https://github.com/GCS-ZHN/diamond4py/issues
Classifier: Programming Language :: Python :: 3
Classifier: License :: OSI Approved :: GNU General Public License v3 (GPLv3)
Classifier: Operating System :: OS Independent
Classifier: Topic :: Scientific/Engineering :: Bio-Informatics
Requires-Python: >=3.7
License-File: LICENSE
